appanzhuoz/__init__.py
appanzhuoz/__main__.py
appanzhuoz-0.1.0.dist-info/METADATA
appanzhuoz-0.1.0.dist-info/WHEEL
appanzhuoz-0.1.0.dist-info/top_level.txt
appanzhuoz-0.1.0.dist-info/RECORD
