Metadata-Version: 2.4
Name: appanzhuoz
Version: 0.1.0
Summary: Add your description here
Requires-Python: >=3.10
Requires-Dist: toml>=0.10.2
